Workbook

Sheet Sheet1
A1: sentiment | B1: target_person | C1: target_party | D1: favorability | E1: topic | F1: location | G1: dtname | H1: latitude | I1: longitude | J1: emotion | K1: text
A2: neutral | B2: Ramesh Peruvazhudi | C2: NTK | D2: neutral | E2: nomination filing / candidate nomination | F2: Kallakurichi, Tamil Nadu | G2: Kallakurichi | H2: 11.738 | I2: 78.964 | J2: neutral | K2: Kallakurichi, Tamil Nadu: Naam Tamilar Katchi candidate Ramesh Peruvazhudi filed his nomination for the Sankarapuram Assembly constituency on the first day of nomination filing for the upcoming Tamil Nadu elections. He reached the election office in a procession from https://t.co/H7AlpTKkTr
A3: positive | B3: Jayasudha Lakshmi Kandan | C3: AIADMK | D3: positive | E3: candidate announcement / celebration | F3: Arani, Tamil Nadu | G3: Arani | H3: 12.6677 | I3: 79.2833 | J3: celebratory | K3: Arani, Tamil Nadu: AIADMK cadres celebrated the announcement of Jayasudha Lakshmi Kandan as the party’s candidate for the Arani Assembly constituency in the 2026 elections by bursting crackers and distributing sweets. https://t.co/GTuz8lI5mT
A4: positive | B4: Vijay | C4: TVK | D4: positive | E4: candidate selection / emotional moment | F4: Tamil Nadu | G4: General | J4: emotional | K4: Tamil Nadu Election: Vijay Gives Driver's Son Poll Ticket, Emotional Moment On Stage Goes Viral #TNPolls #Elections #TamilNadu #TVK #Vijay https://t.co/zmL1PrV6sh
A5: neutral | B5: Vijay | C5: TVK | D5: neutral | E5: political competition / three-cornered contest | F5: Chennai | G5: General | J5: curious | K5: #Janadesh | Can Vijay’s entry into Tamil Nadu politics turn the traditional DMK vs AIADMK contest into a three-cornered fight in the 2026 Assembly elections? Correspondent @Akshayanath reports from Chennai. Watch The Full Program: https://t.co/f2AgOehxv5 #TamilNaduElections https://t.co/y75KwPascT
A6: neutral | B6: Party | C6: Information / General Updates | D6: neutral | E6: election schedule / polling hours | F6: Tamil Nadu | G6: General | J6: neutral | K6: Appointment of dates for various stages of elections and fixation of polling hours for all Assembly constituencies in Tamil Nadu https://t.co/EKA16NFcPl
A7: positive | B7: Arun Nehru | C7: DMK | D7: positive | E7: party manifesto / policy | F7: Tiruchirappalli, Tamil Nadu | G7: Tiruchirappalli | H7: 10.7905 | I7: 78.7047 | J7: optimistic | K7: #WATCH | Tiruchirappalli | On release of the party manifesto for Tamil Nadu elections, DMK MP Arun Nehru says," You should see the progressive nature of the manifesto. It is flexible and adaptable to every kind of person..." https://t.co/coNTHJjus2
A8: positive | B8: Arun Nehru | C8: DMK | D8: positive | E8: party manifesto / policy | F8: Chennai, Tamil Nadu | G8: Chennai | H8: 13.0827 | I8: 80.2707 | J8: optimistic | K8: #WATCH | Chennai | On release of the party manifesto for Tamil Nadu elections, DMK MP Arun Nehru says," You should see the progressive nature of the manifesto. It is flexible and adaptable to every kind of person..." https://t.co/IlF2mIbJmk
A9: neutral | B9: Vijay | C9: TVK | D9: neutral | E9: campaigning / roadshow | F9: Chennai, Tamil Nadu | G9: Chennai | H9: 13.0827 | I9: 80.2707 | J9: energetic | K9: #WATCH | Tamil Nadu Elections 2026 | Chennai: TVK chief and actor Vijay conducts a roadshow. He is contesting the State Assembly elections from the Perambur and Trichy East constituencies. #tvk #TVKVijay‌ #TVKVijay‌HQ #chennai #vijay https://t.co/TGebvRq4ir
A10: neutral | B10: M. K. Stalin | C10: DMK | D10: neutral | E10: Tamil Nadu Assembly elections / nomination | F10: Kolathur, Tamil Nadu | G10: Kolathur | H10: 13.121 | I10: 80.215 | J10: neutral | K10: MK Stalin Files Nomination from Kolathur, Aims for Fourth Straight Win in Tamil Nadu Elections https://t.co/j2fziZEd9N https://t.co/HExw9slHt7
A11: neutral | B11: M. K. Stalin | C11: DMK | D11: neutral | E11: Tamil Nadu Assembly elections / nomination | F11: Kolathur, Tamil Nadu | G11: Kolathur | H11: 13.121 | I11: 80.215 | J11: neutral | K11: With the nomination process for the Tamil Nadu Assembly elections formally underway, Chief Minister M. K. Stalin on Monday filed his nomination from the Kolathur constituency, where he is seeking a fourth consecutive term. #OmmcomNews https://t.co/PqfmODiLkO
A12: positive | B12: M. K. Stalin | C12: DMK | D12: positive | E12: election campaign / voter support | F12: Tamil Nadu | G12: General | J12: optimism | K12: #Exclusive | "Have contested elections more than three times, and I'm seeing greater support the fourth time": Tamil Nadu CM MK Stalin #BattleForTamilNadu #TamilNaduPolitics #AssemblyPolls https://t.co/rUAXBPWLTA
A13: neutral | B13: Vijay | C13: TVK | D13: neutral | E13: campaign / roadshow | F13: Chennai | G13: General | J13: neutral | K13: #WATCH | Tamil Nadu Elections 2026 | Chennai: TVK chief and actor Vijay conducts a roadshow. He is contesting the State Assembly elections from the Perambur and Trichy East constituencies. (Video Source: TVK) https://t.co/Xrd1rHdenz
A14: neutral | B14: Vijay | C14: TVK | D14: neutral | E14: campaign / roadshow | F14: Chennai | G14: General | J14: neutral | K14: #WATCH | Tamil Nadu Elections 2026 | Chennai: TVK chief and actor Vijay conducts a roadshow. He is contesting the State Assembly elections from the Perambur and Trichy East constituencies. (Video Source: TVK) https://t.co/Xrd1rHdenz
A15: negative | B15: Suryakant | D15: negative | E15: elections / internet disruption | F15: Tamil Nadu | G15: General | J15: sarcasm | K15: @Aunindyo2023 Sporadic 3G till a month before US midterms after Tamil Nadu elections? Suryakant will also relish it.
A16: neutral | B16: Party | C16: DMK | D16: neutral | E16: candidate list / elections | F16: Tamil Nadu | G16: General | J16: neutral | K16: 🗳️ Tamil Nadu Assembly Elections 2026 Update Dravida Munnetra Kazhagam (DMK) ने 2026 विधानसभा चुनाव के लिए अपने उम्मीदवारों की पूरी सूची जारी कर दी है। 📅 मतदान: 23 अप्रैल 2026 #TamilNaduElections2026 #DMK #MKStalin #UdhayanidhiStalin #MissyNEWSDECODE https://t.co/bAJlT0frmj
A17: positive | B17: M. K. Stalin | C17: DMK | D17: positive | E17: nomination / election roadmap | F17: Kolathur, Chennai, Tamil Nadu | G17: Kolathur | H17: 13.121 | I17: 80.215 | J17: optimism | K17: Tamil Nadu politics update 🇮🇳 M. K. Stalin ne Chennai ke Kolathur se 23 April ko hone wale Tamil Nadu Assembly elections ke liye nomination file kar diya। “game-changing” roadmap hai. #TamilNadu #MKStalin #DMK #Election2026 #TamilNaduPolitics #MissyNEWSDECODE https://t.co/WAUycifyJD
A18: neutral | B18: Party | D18: neutral | E18: Home voting / General Elections 2026 | F18: Assam, Kerala, Puducherry, Tamil Nadu, West Bengal | G18: General | J18: neutral | K18: General Elections to Legislative Assemblies of Assam , Kerala, Puducherry, Tamil Nadu and West Bengal and bye-elections in 6 states 2026: Over 2.3 lakh Electors to avail the Home Voting Read more : https://t.co/GxJe7rDgqo… https://t.co/mabYGuvuup
A19: positive | B19: Kanimozhi N. V. N. Somu | C19: DMK | D19: positive | E19: Election nominations / predicted victory | F19: Chennai, Tamil Nadu | G19: Chennai | H19: 13.0827 | I19: 80.2707 | J19: confident | K19: Chennai Tamil Nadu: DMK MP Kanimozhi N. V. N. Somu says, ''DMK didn't get geared up for elections today. It's our leader who's going to have a landslide victory of 200 constituencies have filed the nomination today on the starting of the first day. That is something which we are https://t.co/lWTfvKmA6I
A20: positive | B20: M.K. Stalin | C20: DMK | D20: positive | E20: Nomination filing / Assembly elections | F20: Kolathur, Tamil Nadu | G20: Kolathur | H20: 13.121 | I20: 80.215 | J20: confident | K20: ‘Victory Margin Will be Very Big This Time’: CM Stalin Files Nomination From Kolathur Constituency For Tamil Nadu Assembly elections https://t.co/qjCSts8n1l https://t.co/s21bjbFPsR
A21: positive | B21: M.K. Stalin | C21: DMK (alliance) | D21: positive | E21: Alliance readiness for Assembly elections | F21: Chennai, Tamil Nadu | G21: Chennai | H21: 13.0827 | I21: 80.2707 | J21: confident | K21: Chennai, Tamil Nadu: DMK President and Chief Minister M.K. Stalin said the Secular Progressive Alliance is fully prepared for the upcoming Assembly elections, following a meeting at Anna Arivalayam. He noted that the alliance is long-standing and has contested multiple elections https://t.co/C86BITRvft
A22: positive | B22: M. Sudhakaran | C22: TVK | D22: positive | E22: Campaign rally / public procession | F22: Ulundurpet, Tamil Nadu | G22: Ulundurpet | H22: =VLOOKUP(G22,Sheet4!A:C,2,0) -> 11.6932 | I22: =VLOOKUP(G22,Sheet4!A:C,3,0) -> 79.287 | J22: celebratory | K22: Ulundurpet, Tamil Nadu: Tamilaga Vettri Kazhagam (TVK) candidate M. Sudhakaran received a grand welcome in the Ulundurpet constituency ahead of the Assembly elections. Arriving from Chennai, he was greeted by thousands of supporters in a large procession from the toll plaza to https://t.co/mtx5dAoVkD
A23: neutral | B23: T.S. Vakeel Ahmed | C23: DMK++ | D23: neutral | E23: Alliance support / demands (prisoner release, reservation) | F23: Tamil Nadu | G23: General | J23: neutral | K23: @ndmehta19 @TelanganaMaata @Mahaveer_VJ Yes, the claim is true. AIMIM Tamil Nadu unit leaders (State President T.S. Vakeel Ahmed and team) met CM M.K. Stalin yesterday and extended support to the DMK-Congress alliance for the 2026 assembly elections. They raised two demands: release of Muslim prisoners and 7%
A24: positive | B24: Rakesh | C24: TVK | D24: positive | E24: Candidate confidence / upcoming election | F24: Harur (SC), Dharmapuri, Tamil Nadu | G24: Dharmapuri | H24: =VLOOKUP(G24,Sheet4!A:C,2,0) -> 12.1277 | I24: =VLOOKUP(G24,Sheet4!A:C,3,0) -> 78.1579 | J24: confident | K24: Dharmapuri, Tamil Nadu: TVK candidate Rakesh, contesting from the Harur (SC) Assembly constituency, expressed confidence of a decisive victory in the upcoming elections. In an interview, he said previous representatives failed to fulfill development promises and assured that, if https://t.co/4PYKSsdI5p
A25: neutral | B25: Vijay | C25: TVK | D25: neutral | E25: Battleground constituency / election contest (Perambur) | F25: Perambur, North Chennai, Tamil Nadu | G25: Perambur | H25: 13.0827 | I25: 80.2707 | J25: anticipatory | K25: South Central | The Perambur constituency has become the battleground seat of the 2026 Tamil Nadu elections. With the actor-turned-politician Vijay contesting from this seat, all eyes remain on this working-class hub in North Chennai Watch this special on-ground report by https://t.co/5CVGLNZxHN
A26: neutral | B26: Vijay | C26: TVK | D26: neutral | E26: asset declaration / poll affidavit | F26: Tamil Nadu | G26: General | J26: informative | K26: Tamil Nadu Assembly Elections: TVK Chief Vijay Declares Rs 520 Crore Assets In Poll Affidavit #TamilNaduAssemblyElections https://t.co/ftLxdzIIYK
A27: neutral | B27: Vijay | C27: TVK | D27: neutral | E27: candidate announcements / nominations | F27: Tamil Nadu | G27: General | J27: emotional | K27: Actor and 'Tamizhaga Vettri Kazhagam' chief Vijay announced his candidates for the 234 assembly seats ahead of the upcoming elections in Tamil Nadu. Among these candidates was Sabarinathan, the son of his former driver and current PA, Rajendran. As both father and son welled up https://t.co/59A2pWI6L3
A28: neutral | B28: Udhayanidhi Stalin | C28: DMK | D28: neutral | E28: campaigning for candidate | F28: Kanchipuram, Tamil Nadu | G28: Kanchipuram | H28: =VLOOKUP(G28,Sheet4!A:C,2,0) -> 12.8342 | I28: =VLOOKUP(G28,Sheet4!A:C,3,0) -> 79.7036 | J28: informative | K28: VIDEO | Kanchipuram: Tamil Nadu Deputy Chief Minister Udhayanidhi Stalin campaigns for DMK candidate Nithya Sugumar ahead of the upcoming state legislative assembly elections scheduled for April 23. (Full video available on PTI Videos - https://t.co/n147TvrpG7) https://t.co/zHVgCnVjcZ
A29: positive | B29: Party | D29: neutral | E29: elections (humorous commentary) | F29: Bangalore / Tamil Nadu | G29: General | J29: amused | K29: Yesterday was at the Def Leppard concert in Bangalore where the warm up act was "Thermal and a Quarter". In Tamil Nadu elections the warm up act is "Biryani and a quarter" 😀
A30: neutral | B30: Party | D30: neutral | E30: personal branding in state elections | F30: West Bengal; Tamil Nadu; Assam; Kerala | G30: General | J30: informative | K30: New face of governance: How personal branding is reshaping state elections In the election-bound states West Bengal, Tamil Nadu, Assam and Kerala, the image built around the incumbents looms large ✍️ @pratulsharmaa Read: https://t.co/oG1rQ0V82Y (Indian politics, personal
A31: neutral | B31: Vijay | C31: TVK | D31: neutral | E31: entry into politics / candidate selection | F31: Tamil Nadu | G31: General | J31: controversial | K31: Vijay, popularly known as “Thalapathy” (meaning leader), has stepped into active politics with his party. For the 2026 Tamil Nadu Assembly elections, he announced his list of candidates, one of whom is the son of his former driver. The decision has sparked widespread discussion, https://t.co/bVaXIBP9Lo
A32: negative | B32: Vijay | C32: TVK | D32: unfavorable | E32: opposition campaigning / contested seat (Perambur) | F32: Perambur, Tamil Nadu | G32: Perambur | H32: =VLOOKUP(G32,Sheet4!A:C,2,0) -> 13.1186 | I32: =VLOOKUP(G32,Sheet4!A:C,3,0) -> 80.2337 | J32: oppositional | K32: Tamil Nadu Election: Perambur Heats Up Early As Famous Actress Campaigns Against Vijay #TNPolls #elections #tamilnadu #TVK #Vijay https://t.co/v17KCTmyry
A33: neutral | B33: Party | C33: AIADMK++ | D33: neutral | E33: release of final candidate list | F33: Tamil Nadu | G33: General | J33: informative | K33: Tamil Nadu elections 2026: PMK releases final list of candidates | Check here https://t.co/ibngB58VpR #inqalabNews #india https://t.co/fMhAzqeOHk
A34: neutral | B34: M. K. Stalin | C34: DMK | D34: neutral | E34: Tamil Nadu Assembly Elections | F34: Kolathur, Chennai, Tamil Nadu | G34: Kolathur | H34: 13.121 | I34: 80.215 | J34: neutral | K34: 🎥 | WATCH | Tamil Nadu CM M. K. Stalin filed his nomination as DMK candidate from the Kolathur constituency in Chennai for the Assembly elections. @mkstalin #MKStalin #DMK #TamilNaduElections #Chennai #Kolathur #IndianPolitics #TheStatesman https://t.co/4yAzz4rrhm
A35: neutral | B35: Vijay | C35: TVK | D35: neutral | E35: Tamil Nadu Assembly Elections | F35: Perambur and Trichy East, Tamil Nadu | G35: Tiruchirappalli | H35: =VLOOKUP(G35,Sheet4!A:C,2,0) -> 10.7905 | I35: =VLOOKUP(G35,Sheet4!A:C,3,0) -> 78.7047 | J35: neutral | K35: నామినేషన్ వేసిన టీవీకే అధినేత విజయ్..పెరంబూర్, తిరుచ్చి ఈస్ట్ నుండి పోటీ! Vijay Contests From Perambur &amp; Trichy East, Files Nomination | Tamil Nadu Elections 2026 #TVKVijay‌ #vijaythalapathy #TVK‌ #perambur #TrichyEast #TamilNaduElections #tamilnadu #LatestNews #BreakingNews https://t.co/OauHNaqFcJ
A36: positive | B36: Vijay | C36: TVK | D36: positive | E36: Tamil Nadu Assembly Elections | F36: Perambur, Tamil Nadu | G36: Perambur | H36: =VLOOKUP(G36,Sheet4!A:C,2,0) -> 13.1186 | I36: =VLOOKUP(G36,Sheet4!A:C,3,0) -> 80.2337 | J36: hopeful | K36: Actor-turned-politician Vijay Monday filed his nomination papers from the Perambur Assembly constituency, marking a significant milestone in his political journey ahead of the Tamil Nadu Assembly elections. #Vijay #Nomination #Perambur #Politics #TamilNadu #OrissaPOST 📲 https://t.co/PUnWDRLX27
A37: neutral | B37: Vijay | C37: TVK | D37: neutral | E37: Tamil Nadu Assembly Elections | F37: Perambur and Trichy East; Chennai, Tamil Nadu | G37: Tiruchirappalli | H37: 13.0827 | I37: 80.2707 | J37: neutral | K37: #WATCH | Tamil Nadu Elections 2026 | Chennai: TVK chief Vijay conducts a roadshow after filing his nomination. He is contesting the State Assembly elections from Perambur and Trichy East constituencies. (Video Source: TVK) https://t.co/RqYdKDuVlc
A38: neutral | B38: M. K. Stalin | C38: DMK | D38: neutral | E38: Tamil Nadu Assembly Elections | F38: Kolathur, Chennai, Tamil Nadu | G38: Kolathur | H38: 13.121 | I38: 80.215 | J38: neutral | K38: Tamil Nadu Assembly Elections | Chennai: Tamil Nadu CM MK Stalin files his nomination as DMK candidate from Kolathur constituency. https://t.co/vbZKAXDBbE
A39: neutral | B39: M. K. Stalin | C39: DMK | D39: neutral | E39: Tamil Nadu Assembly Elections | F39: Kolathur; Perambur; Trichy East, Tamil Nadu | G39: Tiruchirappalli | H39: =VLOOKUP(G39,Sheet4!A:C,2,0) -> 10.7905 | I39: =VLOOKUP(G39,Sheet4!A:C,3,0) -> 78.7047 | J39: neutral | K39: ತಮಿಳುನಾಡು ಚುನಾವಣೆ: ಕೊಳತ್ತೂರಿನಿಂದ ನಾಮಪತ್ರ ಸಲ್ಲಿಸಿದ ಸಿಎಂ ಎಂ.ಕೆ.ಸ್ಟಾಲಿನ್; ನಟ ವಿಜಯ್ ಸಹ ಚುನವಣಾ ಪ್ರವೇಶ | Tamil Nadu elections https://t.co/uyEK4jyJGH #TamilNaduelections #CMMKStalin #filesnomination #Kolathur #ActorVijay #Vijayavani #KannadaNews
A40: positive | B40: Vijay | C40: TVK | D40: positive | E40: Tamil Nadu Assembly Elections | F40: Perambur and Trichy East; Kolathur, Tamil Nadu | G40: Tiruchirappalli | H40: =VLOOKUP(G40,Sheet4!A:C,2,0) -> 10.7905 | I40: =VLOOKUP(G40,Sheet4!A:C,3,0) -> 78.7047 | J40: excited | K40: 🔴 ELECTIONS 2026 🗳️ Tamil Nadu Elections హాట్! Vijay Perambur &amp; Trichy East నుండి Contest చేస్తున్నారు CM Stalin Kolathur నుండి Nomination దాఖలు చేశారు ✅ #ForTeluguNews #TamilNaduElections2026 #Vijay #tamil
A41: neutral | B41: Vijay | C41: TVK | D41: neutral | E41: Tamil Nadu Assembly Elections | F41: Perambur and Trichy East, Tamil Nadu | G41: Tiruchirappalli | H41: =VLOOKUP(G41,Sheet4!A:C,2,0) -> 10.7905 | I41: =VLOOKUP(G41,Sheet4!A:C,3,0) -> 78.7047 | J41: neutral | K41: Tamil Nadu Elections 2026: Actor Vijay Files Nomination from Perambur, to Contest Trichy East Too #TVKVijay‌ #vijaythalapatty #TamilNaduPolls https://t.co/AQEB4Yhwiv
A42: neutral | B42: Abdul Hakim | C42: NTK | D42: neutral | E42: nomination / elections | F42: Madurai, Tamil Nadu | G42: Madurai | H42: 9.9252 | I42: 78.1198 | J42: neutral | K42: Correction: As the filing of nominations for the Tamil Nadu Legislative Assembly elections began today, Abdul Hakim, the Naam Tamilar Katchi (NTK) candidate for the Madurai Central constituency, became the first to file his nomination at the Madurai Zone III office
A43: negative | B43: Election Commission of India (TNelectionsCEO/ECISVEEP) | D43: unfavorable | E43: election integrity / free and fair elections | F43: Tamil Nadu | G43: General | J43: concern | K43: @arunraajkg @ECISVEEP - As a citizen, I’m concerned about public confidence in ensuring free and fair elections in Tamil Nadu. This is an important moment to reinforce trust through strong and impartial action. @TNelectionsCEO - losing confidence in the process already as a private citizen.
A44: neutral | B44: Udayanidhi Stalin | C44: DMK | D44: neutral | E44: campaign / elections | F44: Kanchipuram, Tamil Nadu | G44: Kanchipuram | H44: =VLOOKUP(G44,Sheet4!A:C,2,0) -> 12.8342 | I44: =VLOOKUP(G44,Sheet4!A:C,3,0) -> 79.7036 | J44: neutral | K44: #WATCH | Tamil Nadu Deputy Chief Minister and DMK Youth Wing Secretary Udayanidhi Stalin holds election campaign in Kanchipuram Legislative Assembly elections will be held in Tamil Nadu on 23 April 2026 to elect all 234 members of the Tamil Nadu Legislative Assembly. Counting of https://t.co/nOp69FK2cp
A45: neutral | B45: Udhayanidhi Stalin | C45: DMK | D45: neutral | E45: campaign / rally | F45: Kanchipuram district, Tamil Nadu | G45: Kanchipuram | H45: =VLOOKUP(G45,Sheet4!A:C,2,0) -> 12.8342 | I45: =VLOOKUP(G45,Sheet4!A:C,3,0) -> 79.7036 | J45: neutral | K45: Udhayanidhi Stalin, the Deputy Chief Minister of Tamil Nadu, addresses a rally | WATCH He is launching his campaign for the upcoming Assembly elections from Kanchipuram district in Tamil Nadu. He will be speaking in support of candidates from that district...- @dharannniii https://t.co/KYIPFhG3yD
A46: neutral | B46: Udayanidhi (Udhayanidhi) Stalin | C46: DMK | D46: favorable | E46: welfare scheme / elections | F46: Kanchipuram, Tamil Nadu | G46: Kanchipuram | H46: =VLOOKUP(G46,Sheet4!A:C,2,0) -> 12.8342 | I46: =VLOOKUP(G46,Sheet4!A:C,3,0) -> 79.7036 | J46: approval | K46: Kanchipuram, Tamil Nadu: Deputy Chief Minister and DMK Youth Wing Secretary Udayanidhi Stalin says, "... For the past three years, we have been providing a monthly assistance of ₹1,000 to women. The BJP and AIADMK attempted to halt this initiative by citing the elections; https://t.co/cJYxSxvzkc
A47: neutral | B47: G. Janakiraman | C47: NTK | D47: neutral | E47: nomination / elections | F47: Chengalpattu / Maduranthakam, Tamil Nadu | G47: Chengalpattu | H47: =VLOOKUP(G47,Sheet4!A:C,2,0) -> 12.6819 | I47: =VLOOKUP(G47,Sheet4!A:C,3,0) -> 79.9888 | J47: neutral | K47: Chengalpattu, Tamil Nadu: Naam Tamilar Katchi candidate G. Janakiraman filed his nomination papers for the Maduranthakam (Reserved) Assembly constituency today, accompanied by party members ahead of the upcoming elections https://t.co/GoBOrUkXqH
A48: neutral | B48: Vijay | C48: TVK | D48: neutral | E48: nomination / campaign | F48: Perambur, Tamil Nadu | G48: Perambur | H48: =VLOOKUP(G48,Sheet4!A:C,2,0) -> 13.1186 | I48: =VLOOKUP(G48,Sheet4!A:C,3,0) -> 80.2337 | J48: enthusiasm | K48: Actor-politician Vijay files nomination from Perambur, drawing massive crowds ahead of Tamil Nadu Assembly elections. 🔗 Read more:https://t.co/09hGtQsaep #Vijay #TamilNaduPolitics #TVK #Perambur #TNAssemblyElections #IndiaPolitics #Election2026 #PoliticalNews #BreakingNews
A49: neutral | B49: Election Commission of India (ECI) | D49: neutral | E49: election schedule / home voting | F49: Assam, Kerala, Puducherry, Tamil Nadu, West Bengal | G49: General | J49: neutral | K49: General Elections and bye-elections 2026: Over 2.3 lakh Electors to avail the Home Voting ✴️Election Commission of India (ECI) announced the schedule for the General Election to Legislative Assemblies of Assam, Kerala, Puducherry, Tamil Nadu and West Bengal and bye- elections in
A50: negative | B50: Party | C50: BJP | D50: unfavorable | E50: Tamil Nadu state elections / community-based appeals | F50: Tamil Nadu | G50: General | J50: anger | K50: Brahmins should vote wisely. No BJP for sure. AIMIM Tamil Nadu Unit announces support to DMK-Congress Alliance in upcoming Tamil Nadu state elections 2 Demands are placed: 1. Release of Muslim Prisoners (Yes, you read it right) 2. 7% Reservations for Muslims India is a
A51: neutral | B51: Vijay; M. K. Stalin | C51: General | D51: neutral | E51: candidate nominations / Tamil Nadu Assembly Elections | F51: Tamil Nadu | G51: General | J51: neutral | K51: #WATCH | Vijay, chief of Tamilaga Vettri Kazhagam, files nominations from Tiruchirappalli East and Perambur, while M. K. Stalin submits his papers from Kolathur constituency for the Tamil Nadu Assembly Elections. Stay updated with all the stories that matter — download the https://t.co/ci3WE9mIEo
A52: positive | B52: M. K. Stalin | C52: DMK | D52: favorable | E52: nomination filing / Tamil Nadu elections | F52: Tamil Nadu | G52: General | J52: confident | K52: Delhi vs Tamil Nadu! TN CM M. K. Stalin sends a strong message after filing nomination ahead of assembly elections.#DelhiVsTamilNadu #MKStalin #TamilNaduElections #AssemblyElections #PoliticalNews #IndiaPolitics #Election2026 #DMK #BreakingNews #NominationFiled #PoliticalUpdate https://t.co/4hbw84QqRh
A53: negative | B53: Party | C53: BJP | D53: unfavorable | E53: election results / BJP in Tamil Nadu | F53: Tamil Nadu | G53: General | J53: gloating | K53: @bhatnaturally Dude, people rejected him in coimbatore parliamentary elections. People get what they deserve. Tamil nadu is not ready for the BJP. THEIR LOSS.
A54: neutral | B54: Vijay | C54: TVK | D54: neutral | E54: nomination filing / Tamil Nadu elections | F54: Tamil Nadu | G54: General | J54: neutral | K54: With Tamil Nadu Assembly elections nearing closer, Tamilaga Vettri Kazhagam (TVK) President Vijay on Monday filed his nomination from the Perambur and Trichy East constituencies. https://t.co/PNXFMCU7bA
A55: neutral | B55: Vijay | C55: TVK | D55: neutral | E55: campaign roadshow / Tamil Nadu elections | F55: Chennai, Tamil Nadu | G55: Chennai | H55: 13.0827 | I55: 80.2707 | J55: neutral | K55: TVK Chief Vijay's roadshow in Chennai after filing nomination for Tamil Nadu elections: https://t.co/BLNgdizcHE https://t.co/C55DT9SmFa
A56: neutral | B56: Party | D56: neutral | E56: election notification / Assembly elections | F56: Tamil Nadu; West Bengal | G56: General | J56: neutral | K56: The Election Commission of India today issued the notification for the Assembly elections in Tamil Nadu and the first phase of polling in West Bengal, formally setting the electoral process in motion in both states. With the notification in place, the filing of nomination papers https://t.co/QmqoKzc1LK
A57: neutral | B57: Party | D57: neutral | E57: filing of nominations / Tamil Nadu Legislative Assembly Elections 2026 | F57: Tamil Nadu | G57: General | J57: neutral | K57: Elections Alert 🚨 Filing of nominations for the #Tamil Nadu Legislative Assembly Elections 2026 began today with issue of gazette notification चुनाव अलर्ट 🚨 तमिलनाडु विधान सभा आम चुनाव 2026 की अधिसूचना जारी होने के साथ ही नामांकन दाखिला आज से शुरू #Election2026 #ECI https://t.co/N9wsZZ0VeQ
A58: negative | B58: President of India | D58: favorable | E58: law and order / election administration | F58: Tamil Nadu | G58: General | J58: anger | K58: @rashtrapatibhvn To ensure fair elections in Tamil Nadu President’s Rule should be imposed and Central Forces should replace the local Police to maintain law and order.
A59: neutral | B59: Party | C59: AIADMK | D59: neutral | E59: electoral alliances | F59: Tamil Nadu | G59: General | J59: neutral | K59: Tamil Nadu Election: From AIADMK-Led NDA To Ruling DMK, What Do The Alliances Look Like? #TamilNadu #AIADMK #DMK #Elections https://t.co/QQutdymkhC
A60: positive | B60: M.K. Stalin | C60: DMK | D60: favorable | E60: campaigning / election launch | F60: Chennai / Tiruvarur, Tamil Nadu | G60: Tiruvarur | H60: 13.0827 | I60: 80.2707 | J60: respectful | K60: Chennai, Tamil Nadu: Ahead of launching the campaign for the upcoming Legislative Assembly elections from Tiruvarur district tomorrow, DMK President and Chief Minister M.K. Stalin paid homage at the memorials of former Chief Ministers C.N. Annadurai and M. Karunanidhi located on https://t.co/ArJ56QVIaq
A61: positive | B61: Party | C61: BJP | D61: favorable | E61: elections (Assembly 2026) | F61: India (Assam, Kerala, Tamil Nadu, West Bengal, Puducherry) | G61: General | J61: optimism | K61: 🧵 India Assembly Elections 2026 – Ground Reality The Election Commission of India has set the stage for elections across Assam, Kerala, Tamil Nadu, West Bengal &amp; Puducherry (824 seats) — and the momentum clearly favours the BJP-led NDA. 📅 Polling: April 9, 23 &amp; 29 | 🗳️
A62: neutral | B62: Vijay | C62: TVK | D62: neutral | E62: candidate nominations | F62: Tamil Nadu | G62: General | J62: controversy | K62: Vijay, popularly known as “Thalapathy” (meaning leader), has stepped into active politics with his party. For the 2026 Tamil Nadu Assembly elections, he announced his list of candidates, one of whom is the son of his former driver. The decision has sparked widespread discussion,
A63: neutral | B63: Vijay | C63: TVK | D63: neutral | E63: candidate nomination | F63: Tamil Nadu | G63: General | J63: neutral | K63: Tamil Nadu ની ચૂંટણી પહેલા, વિજયે તેમના ડ્રાઇવરના પુત્રને ધારાસભ્ય ઉમેદવાર તરીકે નોમિનેટ કર્યા https://t.co/2yTrF40BSS #Ahead #TamilNadu #Elections #Vijay #nominated #hisdriver #son #asMLAcandidate #ShriNutanSaurashtra #NutanSaurashtra
A64: negative | B64: Rahul (Gandhi) | C64: INC | D64: unfavorable | E64: opposition unity / elections | F64: Puducherry, Tamil Nadu, West Bengal, Kerala (India) | G64: General | J64: frustration | K64: Thanks to Rahul's recent shenanigans in pondicherry, Tamil nadu, WB and Kerala assembly elections, we shall say that a united opposition is non-existent. https://t.co/TRf0Xjanp1 https://t.co/WIEhE3edK4
A65: positive | B65: Vijay | C65: TVK | D65: favorable | E65: celebrity endorsements / election support | F65: Tamil Nadu | G65: General | J65: support | K65: Kollywood actress #VaniBhojan, actors #Jai and #SibiSathyaraj have come out in support of #ThalapathyVijay contesting in the Tamil Nadu Elections 2026.
A66: neutral | B66: Vijay | C66: TVK | D66: neutral | E66: Tamil Nadu Assembly nomination filing | F66: Perambur (Chennai); Tiruchi East (Tiruchirappalli), Tamil Nadu | G66: Tiruchirappalli | H66: 13.0827 | I66: 80.2707 | J66: neutral | K66: Actor-turned-politician Vijay has officially filed his nomination for the upcoming Tamil Nadu Assembly elections. The debutante will contesting from two urban constituencies - Perambur in Chennai and Tiruchi East. Vijay has also formally introduced all 234 candidates of his
A67: neutral | B67: Vijay, M. K. Stalin | D67: neutral | E67: Political face-off / nomination filings | F67: Tamil Nadu | G67: General | J67: neutral | K67: Tamil Nadu Elections 2026: Vijay Files Nomination Same Day as MK Stalin, Sets Up Symbolic Political Face-Off https://t.co/3rzU7VFwvt #TamilNaduElections2026 #Vijay #MKStalin #PoliticalFaceOff #ElectionNomination #TNPolitics #oneindia #politicstoday #election2026 #TNELECTION2026 https://t.co/Up7Atw3b5m
A68: neutral | B68: Party | D68: neutral | E68: Filing of nominations for Assembly elections | F68: Tamil Nadu; West Bengal | G68: General | J68: neutral | K68: Filing of nominations begins today for Tamil Nadu and West Bengal Assembly elections https://t.co/fsPq6q2TnU
A69: negative | B69: Party | C69: BJP | D69: negative | E69: Election defeats and potential party appointment | F69: Tamil Nadu | G69: General | J69: disapproval | K69: @bhatnaturally He was rejected by the people of Tamil Nadu in 2021 and 2024 elections. If he follows BJP high command, he could get a respectable post else BJP won't lose anything.
A70: neutral | B70: M. K. Stalin | C70: DMK | D70: neutral | E70: Nomination filing for Kolathur constituency | F70: Kolathur, Chennai, Tamil Nadu | G70: Kolathur | H70: 13.121 | I70: 80.215 | J70: neutral | K70: 🎥 | WATCH | Tamil Nadu CM M. K. Stalin filed his nomination as DMK candidate from the Kolathur constituency in Chennai for the Assembly elections. @mkstalin @arivalayam #MKStalin #DMK #TamilNaduElections #Chennai #Kolathur #IndianPolitics #TheStatesman https://t.co/HwJ89fVg2k
A71: neutral | B71: M. K. Stalin | C71: DMK | D71: neutral | E71: Nomination filing for Kolathur constituency | F71: Kolathur, Chennai, Tamil Nadu | G71: Kolathur | H71: 13.121 | I71: 80.215 | J71: neutral | K71: Tamil Nadu Chief Minister @mkstalin on Monday filed his nomination papers from the Kolathur Assembly constituency, formally entering the fray for the upcoming Tamil Nadu Assembly elections. Accompanied by senior leaders and party workers, Stalin arrived at the designated https://t.co/tGSx9mjzdy
A72: neutral | B72: Vijay | C72: TVK | D72: neutral | E72: Roadshow after nomination filing | F72: Chennai; Perambur and Trichy East constituencies, Tamil Nadu | G72: Tiruchirappalli | H72: 13.0827 | I72: 80.2707 | J72: neutral | K72: #WATCH | Tamil Nadu Elections 2026 | Chennai: Supporters and fans of TVK chief and actor Vijay flank him as he conducts a roadshow after filing his nomination. He is contesting the State Assembly elections from Perambur and Trichy East constituencies. (Video Source: TVK) https://t.co/148T0d0MWy
A73: neutral | B73: K. N. Nehru | C73: DMK | D73: neutral | E73: Nomination filing for Tiruchirappalli West | F73: Tiruchirappalli West, Tamil Nadu | G73: Tiruchirappalli | H73: 10.7905 | I73: 78.7047 | J73: neutral | K73: #WATCH | Tamil Nadu Elections 2026 | Tiruchirappalli | Tamil Nadu Minister KN Nehru files his nomination as DMK candidate from Tiruchirappalli West Assembly Constituency https://t.co/zEzJFJXlC6
A74: neutral | B74: Party | D74: neutral / informational | E74: opinion polls / elections | F74: Tamil Nadu | G74: General | J74: curiosity | K74: Opinion Polls For Tamil Nadu Election 2026: Who Is Leading Right Now? #TamilNadu #Elections https://t.co/MTa2SGbVCX
A75: neutral | B75: Vijay | C75: TVK | E75: constituency focus / candidate contest | F75: Perambur, North Chennai, Tamil Nadu | G75: Perambur | H75: 13.0827 | I75: 80.2707 | J75: interest | K75: South Central | The Perambur constituency has become the battleground seat of the 2026 Tamil Nadu elections. With the actor-turned-politician Vijay contesting from this seat, all eyes remain on this working-class hub in North Chennai. https://t.co/sFTXP6somi
A76: neutral | B76: Vijay | C76: TVK | E76: candidacy / seat announcement | F76: Trichy East & Perambur, Tamil Nadu | G76: Tiruchirappalli | H76: =VLOOKUP(G76,Sheet4!A:C,2,0) -> 10.7905 | I76: =VLOOKUP(G76,Sheet4!A:C,3,0) -> 78.7047 | J76: optimism | K76: 🚨🗳️ : Big Update: Vijay to contest 2026 Tamil Nadu elections from 2 seats — Trichy East &amp; Perambur. 📢 Statement: Can’t campaign everywhere, trusts selected candidates. 👥 Plan: Strong team, focus on growth. 📝 Note: Will use name C. Joseph Vijay. https://t.co/YuxVXFed6d
A77: negative | B77: Party | C77: DMK | D77: negative | E77: campaign dispute / inter-party conflict | F77: Tamil Nadu | G77: General | J77: anger | K77: #BREAKING | Tamil Nadu Elections: TVK accuses DMK of stalling its campaign; DMK hits back, rejecting the charge NDTV's @reethu_journo shares more details on #TheSouthernView with @Vasudha156 https://t.co/kPnG2F5tii
A78: negative | B78: Party | C78: INC | D78: negative | E78: candidate list delay / internal party conflict | F78: Tamil Nadu | G78: General | J78: frustration | K78: @DeccanHerald Why has the Congress still not released its candidate list for the 2026 Tamil Nadu elections? Is the delay due to unresolved internal party conflicts? At this stage, such confusion sends a weak message to the public.
A79: neutral | B79: K.N. Nehru | C79: DMK | E79: nomination filing / candidacy | F79: Tiruchirappalli West, Tamil Nadu | G79: Tiruchirappalli | H79: 10.7905 | I79: 78.7047 | J79: neutral | K79: Tiruchirappalli, Tamil Nadu: DMK leader and Municipal Administration Minister K.N. Nehru filed his nomination from the Tiruchirappalli West constituency as the nomination process for the Assembly elections began. He arrived in a procession with alliance leaders and supporters, https://t.co/gI5IV6MYWe
A80: neutral | B80: Mohanachandran | E80: election administration / inspection | F80: Tiruvarur, Tamil Nadu | G80: Tiruvarur | H80: =VLOOKUP(G80,Sheet4!A:C,2,0) -> 10.7725 | I80: =VLOOKUP(G80,Sheet4!A:C,3,0) -> 79.6368 | J80: neutral | K80: Tiruvarur, Tamil Nadu: District Election Officer and Collector Mohanachandran conducted a surprise inspection at the Tiruvarur RDO Office as nomination filing began for the Assembly elections. He reviewed arrangements, checked availability of forms, and inspected facilities for https://t.co/ZervLTrL11
A81: neutral | B81: Party | E81: nominations / election notifications | F81: Tamil Nadu; West Bengal | G81: General | J81: neutral | K81: Nominations began for assembly elections in Tamil Nadu and West Bengal; the ECI issued official notifications for the multi-phase polls. #ONEPIECE #sfawtde #sabihagökçen #RepúblicaDominicana #MiSelecciónAzteca https://t.co/0br369ECN5
A82: neutral | B82: Vijay | C82: TVK | D82: neutral | E82: nomination/elections | F82: Perambur, Chennai, Tamil Nadu | G82: Perambur | H82: 13.0827 | I82: 80.2707 | J82: informational | K82: #Breaking: TVK chief Vijay has filed his nomination from Perambur in Chennai for the Tamil Nadu Assembly elections. He is also set to contest from Trichy East. #TamilNadu #Vijay #Politics #Election2026 #Chennai #JaagIndia https://t.co/4JigutdMR1
A83: positive | B83: Party | D83: favorable | E83: elections, defense/national security | F83: Tamil Nadu, India | G83: General | J83: optimism | K83: Political activity heats up as Tamil Nadu gears up for elections 🗳️ India approves major defense deals to boost national security 💪 #IndiaNews #TamilNaduElections #Politics #Defense #NationalSecurity 🇮🇳
A84: positive | B84: M. K. Stalin | C84: DMK | D84: favorable | E84: elections/victory | F84: Tamil Nadu | G84: General | J84: confidence | K84: #WATCH | Tamil Nadu Chief Minister #MKStalin expresses confidence of a massive victory in the upcoming April 23 elections, saying that he is witnessing stronger support than in the past three elections. https://t.co/y3ZUWrYCWW
A85: neutral | B85: M. K. Stalin | C85: DMK | D85: neutral | E85: nomination/elections | F85: Kolathur, Tamil Nadu | G85: Kolathur | H85: 13.121 | I85: 80.215 | J85: informational | K85: #TamilNadu Chief Minister and #DMK president #MKStalin has filed his nomination to contest from the #Kolathur Assembly constituency in the 2026 Tamil Nadu Assembly elections. https://t.co/aOpANsJ8dr
A86: negative | B86: Narendra Modi | C86: BJP | D86: unfavorable | E86: campaigning, foreign policy, economy | F86: India (Bengal, Tamil Nadu, Kerala, Assam) | G86: General | J86: concern | K86: @KanwalSibal Modi is very busy campaigning for state elections in Bengal, Tamil Nadu, Kerala &amp; Assam. Once these elections are over, I'm sure Modi will pay attention to the Iran war &amp; related issues, including the faltering economy.
A87: neutral | B87: Party | D87: neutral | E87: electoral rules | F87: Tamil Nadu | G87: General | J87: curiosity | K87: Interesting to know that you can contest in 2 different constituencies in Tamil Nadu in the same Elections #TNElections
A88: neutral | B88: Vijay | C88: TVK | D88: neutral | E88: nomination/political debut | F88: Perambur, Chennai, Tamil Nadu | G88: Perambur | H88: 13.0827 | I88: 80.2707 | J88: anticipation | K88: WATCH LIVE: Vijay TVK Files Nomination Perambur Chennai Tamil Nadu Elections 2026: Political Debut https://t.co/EfkWRwSrHH
A89: neutral | B89: M. K. Stalin, Vijay | C89: General | D89: neutral | E89: elections/nomination | F89: Tamil Nadu | G89: General | J89: anticipation | K89: Big contest in Tamil Nadu elections: CM M. K. Stalin and actor Vijay files nomination for state elections #MKStalin #DMK #TamilNadu #Elections #Vijay #TVK #TamilNaduElections #Breaking https://t.co/nRjWPwC6GW
A90: neutral | B90: Vijay | C90: TVK | D90: neutral | E90: Nomination / Tamil Nadu Assembly Elections 2026 | F90: Perambur, Tiruchirappalli East, Tamil Nadu | G90: Tiruchirappalli | H90: 10.7905 | I90: 78.7047 | J90: anticipation | K90: #WATCH | Nomination Moment 💥 Vijay files his nomination for the Tamil Nadu Assembly Elections 2026 🗳️ He will be contesting from Perambur and Tiruchirappalli East constituencies. 📹 Watch the full video clip of this key moment. 🔥 From filing papers to fighting the battle — https://t.co/Tb50F8iDJq
A91: neutral | B91: M. K. Stalin | C91: DMK | D91: neutral | E91: Nomination / Roadshow | F91: Kolathur, Chennai, Tamil Nadu | G91: Kolathur | H91: 13.121 | I91: 80.215 | J91: neutral | K91: WATCH | Tamil Nadu Assembly Elections | Chennai: Tamil Nadu CM MK Stalin conducts a roadshow after filing his nomination as DMK candidate from Kolathur constituency. https://t.co/2I5dNGPNeg
A92: neutral | B92: Vijay | C92: TVK | D92: neutral | E92: Nomination / Tamil Nadu Elections 2026 | F92: Perambur, Trichy East, Tamil Nadu | G92: Tiruchirappalli | H92: =VLOOKUP(G92,Sheet4!A:C,2,0) -> 10.7905 | I92: =VLOOKUP(G92,Sheet4!A:C,3,0) -> 78.7047 | J92: neutral | K92: #WATCH | Tamil Nadu Elections 2026 | Chennai: TVK chief Vijay files his nomination. He is contesting the State Assembly elections from Perambur and Trichy East constituencies. #TamilNaduPolls #vijay #kalingatv https://t.co/1DaNMi9tqB
A93: neutral | B93: Party | E93: Analysis / 2026 Tamil Nadu Assembly Elections | F93: Tamil Nadu | G93: General | J93: neutral | K93: The Threshold: Decoding the 2026 Tamil Nadu Assembly Elections Vignesh Karthik K.R.✍️ https://t.co/Z6TUoNLgS8
A94: neutral | B94: Vijay | C94: TVK | D94: neutral | E94: Candidates list / Elections | F94: Tamil Nadu | G94: General | J94: neutral | K94: TVK Candidates List for Tamil Nadu Elections 2026: Thalapathy Vijay’s Constituency &amp; Full Details Read more at: https://t.co/XBkNcTnIUH
A95: neutral | B95: Vijay | C95: TVK | D95: neutral | E95: Roadshow / Nomination | F95: Chennai (Perambur, Trichy East), Tamil Nadu | G95: Tiruchirappalli | H95: 13.0827 | I95: 80.2707 | J95: neutral | K95: #WATCH | Tamil Nadu Elections 2026 | Chennai: TVK chief Vijay conducts a roadshow after filing his nomination. He is contesting the State Assembly elections from Perambur and Trichy East constituencies. (Video Source: TVK) https://t.co/SMh9nmfix7
A96: neutral | B96: M. K. Stalin | C96: DMK | D96: neutral | E96: Roadshow / Nomination | F96: Kolathur, Chennai, Tamil Nadu | G96: Kolathur | H96: 13.121 | I96: 80.215 | J96: neutral | K96: Tamil Nadu Assembly Elections | Chennai: Tamil Nadu CM MK Stalin (@mkstalin) conducts a roadshow after filing his nomination as DMK (@arivalayam) candidate from Kolathur constituency. #TamilNaduElections #Elections2026 #AssemblyElections2026 https://t.co/TKizT4W2LR https://t.co/JjnGQQWMuU
A97: neutral | B97: Vijay, M. K. Stalin | C97: General | D97: neutral | E97: Nomination Day / Tamil Nadu Elections | F97: Tamil Nadu (Perambur, Kolathur) | G97: Perambur | H97: =VLOOKUP(G97,Sheet4!A:C,2,0) -> 13.1186 | I97: =VLOOKUP(G97,Sheet4!A:C,3,0) -> 80.2337 | J97: neutral | K97: Tamil Nadu: Big Nomination Day Actor-turned-politician Vijay files nomination for Tamil Nadu polls from Perambur as TVK chief. Tamil Nadu CM M. K. Stalin files nomination from Kolathur for upcoming state elections. #MKStalin #DMK #TamilNadu #Elections #Vijay #TVK https://t.co/dEvxYGwzFr
A98: positive | B98: M.S.R. Raja Varman | C98: AIADMK | D98: favorable | E98: election campaign | F98: Tiruchuli, Tamil Nadu | G98: Tiruchuli | H98: =VLOOKUP(G98,Sheet4!A:C,2,0) -> 9.4833 | I98: =VLOOKUP(G98,Sheet4!A:C,3,0) -> 78.1333 | J98: confident | K98: Tiruchuli, Tamil Nadu: AIADMK candidate M.S.R. Raja Varman expressed strong confidence ahead of the Assembly elections, saying he is determined to win regardless of his opponents. After paying homage to leaders’ statues in the constituency, he said AIADMK’s legacy allows even https://t.co/E6Iq9k5Kt8
A99: neutral | B99: Vinodhini | C99: NTK | D99: neutral | E99: nomination filing | F99: Tiruvarur, Tamil Nadu | G99: Tiruvarur | H99: =VLOOKUP(G99,Sheet4!A:C,2,0) -> 10.7725 | I99: =VLOOKUP(G99,Sheet4!A:C,3,0) -> 79.6368 | J99: respectful | K99: Tiruvarur, Tamil Nadu: Naam Tamilar Katchi (NTK) candidate Vinodhini filed her nomination for the Thiruthuraipoondi (SC) Assembly constituency as the nomination process began for the April 23 elections. Before filing, she paid floral tributes to Dr. B.R. Ambedkar and Kamarajar. https://t.co/cXR6TdVfVh
A100: neutral | B100: Sakkottai K. Anbazhagan | C100: DMK | D100: neutral | E100: nomination filing | F100: Kumbakonam, Tamil Nadu | G100: Kumbakonam | H100: =VLOOKUP(G100,Sheet4!A:C,2,0) -> 10.9617 | I100: =VLOOKUP(G100,Sheet4!A:C,3,0) -> 79.3881 | J100: determined | K100: Kumbakonam, Tamil Nadu: DMK candidate and three-time MLA Sakkottai K. Anbazhagan filed his nomination papers at the Sub-Collector’s office ahead of the April 23 Assembly elections. Seeking a fourth consecutive term, he submitted his papers before the Election Officer and https://t.co/njnwjufKnU
...

Sheet Sheet2
A1: Tamil Nadu | B1: False
A2: Chennai | B2: True
A3: Perambur | B3: True
A4: Kolathur | B4: True
A5: Trichy East | B5: True
A6: Tiruchirappalli | B6: True
A7: Madurai | B7: True
A8: Coimbatore | B8: True
A9: Kanchipuram | B9: True
A10: Chengalpattu | B10: True
A11: Tambaram | B11: True
A12: Tiruvarur | B12: True
... A86: Nepal | B86: False

Sheet Sheet3
A1: Location
A2: Kallakurichi
A3: Arani
A4: Tiruchirappalli
A5: Chennai
A6: Kolathur
A7: Ulundurpet
A8: Dharmapuri
A9: Perambur
A10: Kanchipuram
A11: Madurai
A12: Chengalpattu
... A124: Telugu-speaking region

Sheet Sheet4
A1: Location | B1: Latitude | C1: Longitude
A2: Kallakurichi | B2: 11.7381 | C2: 78.9629
A3: Arani | B3: 12.6683 | C3: 79.2857
A4: Tiruchirappalli | B4: 10.7905 | C4: 78.7047
A5: Chennai | B5: 13.0827 | C5: 80.2707
A6: Kolathur | B6: 13.1245 | C6: 80.215
A7: Ulundurpet | B7: 11.6932 | C7: 79.287
A8: Dharmapuri | B8: 12.1277 | C8: 78.1579
A9: Perambur | B9: 13.1186 | C9: 80.2337
A10: Kanchipuram | B10: 12.8342 | C10: 79.7036
A11: Madurai | B11: 9.9252 | C11: 78.1198
A12: Chengalpattu | B12: 12.6819 | C12: 79.9888
A13: Tamil | B13: FALSE | C13: FALSE
A14: Tiruvarur | B14: 10.7725 | C14: 79.6368
A15: Tamil Nadu | B15: FALSE | C15: FALSE
A16: Tiruchuli | B16: 9.4833 | C16: 78.1333
A17: Kumbakonam | B17: 10.9617 | C17: 79.3881
A18: Ramanathapuram | B18: 9.3716 | C18: 78.8308
A19: Krishnagiri | B19: 12.5266 | C19: 78.2137
A20: Thoothukudi | B20: 8.7642 | C20: 78.1348
A21: Vellore | B21: 12.9165 | C21: 79.1325
A22: Villivakkam | B22: 13.11 | C22: 80.207
A23: Villupuram | B23: 11.9401 | C23: 79.4861
A24: Hosur | B24: 12.7409 | C24: 77.8253
A25: Thanjavur | B25: 10.787 | C25: 79.1378
A26: Coimbatore | B26: 11.0168 | C26: 76.9558
A27: Neelankarai | B27: 12.949 | C27: 80.254
... A45: Tindivanam | B45: 12.2341 | C45: 79.6555
A46: n | B46: FALSE | C46: FALSE
A47: Viluppuram | B47: 11.9401 | C47: 79.4861
A48: Srirangam | B48: 10.862 | C48: 78.6966
A49: Puducherry | B49: 11.9416 | C49: 79.8083
A50: Alandur | B50: 13.004 | C50: 80.201
A51: Perambalur | B51: 11.2342 | C51: 78.8836
A52: Mumbai | B52: 19.076 | C52: 72.8777
A53: Virudhunagar | B53: 9.5851 | C53: 77.9579
A54: Sattur | B54: 9.365 | C54: 77.925
A55: Tamil Nadu | B55: Bengal | C55: FALSE | D55: FALSE
A56: Multiple | B56: FALSE | C56: FALSE
A57: Sankaralingapuram village | B57: 9.5 | C57: 77.8
A58: Theni | B58: 10.0104 | C58: 77.4768
A59: Erode | B59: 11.341 | C59: 77.7172
A60: Salem | B60: 11.6643 | C60: 78.146
A61: Saliyamangalam | B61: 10.897 | C61: 79.264
A62: Tirupparanguntram | B62: 9.881 | C62: 78.072
A63: Thiruvarur | B63: 10.7725 | C63: 79.6368
A64: Dindigul | B64: 10.3673 | C64: 77.9803
A65: Rajapalayam | B65: 9.451 | C65: 77.5533
A66: Salem North | B66: 11.7 | C66: 78.1667
A67: Tiruppur | B67: 11.1085 | C67: 77.3411
A68: Sivakasi | B68: 9.449 | C68: 77.797
... A103: Mannargudi | B103: 10.6667 | C103: 79.45
A104: Nellai to Sattur | B104: FALSE | C104: FALSE
A105: Mayiladuthurai | B105: 11.1035 | C105: 79.655
A106: Arcot | B106: 12.905 | C106: 79.318
A107: Sonmarg | B107: 34.3 | C107: 75.3
A108: Nazarethpet | B108: 13.041 | C108: 80.06
A109: Manali | B109: 13.1667 | C109: 80.2667
A110: Pattavayal | B110: 11.5 | C110: 76.4
A111: Marthandam | B111: 8.3167 | C111: 77.2167
A112: Tennessee | B112: FALSE | C112: FALSE
A113: Telangana | B113: FALSE | C113: FALSE
A114: Mettur | B114: 11.8 | C114: 77.8
A115: Pondicherry | B115: 11.9416 | C115: 79.8083
A116: Velacherry | B116: 12.975 | C116: 80.22
A117: Mamallapuram | B117: 12.6208 | C117: 80.1945
A118: Thiruvananthapuram | B118: 8.5241 | C118: 76.9366
A119: Sivaksai | B119: 9.449 | C119: 77.797
A120: Salem; Thoothukudi | B120: FALSE | C120: FALSE
A121: Nowboicha | B121: 27.3 | C121: 94.4
A122: Odisha | B122: FALSE | C122: FALSE
A123: Nigeria | B123: FALSE | C123: FALSE
